involute/__init__.py
involute-0.0.1.dist-info/METADATA
involute-0.0.1.dist-info/WHEEL
involute-0.0.1.dist-info/top_level.txt
involute-0.0.1.dist-info/RECORD
