Metadata-Version: 2.4
Name: involute
Version: 0.0.1
Summary: A hardware accelerated plotting library
Author: Warren Elrod
License: MIT
Classifier: Programming Language :: Python :: 3
Classifier: License :: OSI Approved :: MIT License
Classifier: Operating System :: OS Independent
Requires-Python: >=3.10
